raman_data/__init__.py
raman_data/datasets.py
raman_data/exceptions.py
raman_data/types.py
raman_data/loaders/HugLoader.py
raman_data/loaders/ILoader.py
raman_data/loaders/KagLoader.py
raman_data/loaders/LoaderTools.py
raman_data/loaders/ZenLoader.py
raman_data/loaders/ZipLoader.py
raman_data/loaders/__init__.py
raman_data-0.0.3.dist-info/licenses/LICENSE
raman_data-0.0.3.dist-info/METADATA
raman_data-0.0.3.dist-info/WHEEL
raman_data-0.0.3.dist-info/top_level.txt
raman_data-0.0.3.dist-info/RECORD
