Metadata-Version: 2.4
Name: raman-data
Version: 0.0.3
Summary: A unified Python package for accessing various Raman spectroscopy datasets.
Author-email: Mario Koddenbrock <mario.koddenbrock@htw-berlin.de>, Oskar Fulde <Oskar.Fulde@Student.HTW-Berlin.de>, Robert Koch <Robert.Koch@Student.HTW-Berlin.de>
Project-URL: Homepage, https://github.com/ml-lab-htw/raman_data
Project-URL: Bug Tracker, https://github.com/ml-lab-htw/raman_data/issues
Classifier: Programming Language :: Python :: 3
Classifier: License :: OSI Approved :: MIT License
Classifier: Operating System :: OS Independent
Classifier: Intended Audience :: Science/Research
Classifier: Topic :: Scientific/Engineering
Requires-Python: >=3.10
License-File: LICENSE
Requires-Dist: aiohappyeyeballs==2.6.1
Requires-Dist: aiohttp==3.12.15
Requires-Dist: aiosignal==1.4.0
Requires-Dist: attrs==25.3.0
Requires-Dist: certifi==2025.8.3
Requires-Dist: charset-normalizer==3.4.3
Requires-Dist: colorama==0.4.6
Requires-Dist: datasets==4.0.0
Requires-Dist: dill==0.3.8
Requires-Dist: filelock==3.19.1
Requires-Dist: frozenlist==1.7.0
Requires-Dist: fsspec==2025.3.0
Requires-Dist: hf-xet==1.1.10
Requires-Dist: h5py==3.14.0
Requires-Dist: huggingface-hub==0.34.4
Requires-Dist: idna==3.10
Requires-Dist: kagglehub==0.3.13
Requires-Dist: multidict==6.6.4
Requires-Dist: multiprocess==0.70.16
Requires-Dist: numpy==2.3.2
Requires-Dist: openpyxl==3.1.5
Requires-Dist: packaging==25.0
Requires-Dist: pandas==2.3.2
Requires-Dist: propcache==0.3.2
Requires-Dist: pyarrow==21.0.0
Requires-Dist: python-dateutil==2.9.0.post0
Requires-Dist: pytz==2025.2
Requires-Dist: PyYAML==6.0.2
Requires-Dist: requests==2.32.5
Requires-Dist: six==1.17.0
Requires-Dist: scipy==1.16.3
Requires-Dist: tqdm==4.67.1
Requires-Dist: typing_extensions==4.15.0
Requires-Dist: tzdata==2025.2
Requires-Dist: urllib3==2.5.0
Requires-Dist: xxhash==3.5.0
Requires-Dist: yarl==1.20.1
Provides-Extra: test
Requires-Dist: pytest; extra == "test"
Dynamic: license-file
